wagtail_stacks/__init__.py
wagtail_stacks/models.py
wagtail_stacks/registered_blocks.py
wagtail_stacks/templates/wagtail_stacks/heading.html
wagtail_stacks/templates/wagtail_stacks/rich_text_block.html
wagtail_stacks-0.2.dist-info/DESCRIPTION.rst
wagtail_stacks-0.2.dist-info/LICENSE.txt
wagtail_stacks-0.2.dist-info/METADATA
wagtail_stacks-0.2.dist-info/RECORD
wagtail_stacks-0.2.dist-info/WHEEL
wagtail_stacks-0.2.dist-info/metadata.json
wagtail_stacks-0.2.dist-info/top_level.txt
