Metadata-Version: 2.0
Name: wagtail-stacks
Version: 0.2
Summary: The base application for Wagtail Stacks.
Home-page: http://stacks.wgbhdigital.org/
Author: Jonathan Ellenberger
Author-email: jonathan_ellenberger@wgbh.org
License: MIT License, see LICENSE
Platform: UNKNOWN
Classifier: Framework :: Django
Classifier: Framework :: Django :: 1.7
Classifier: Framework :: Django :: 1.8
Classifier: License :: OSI Approved :: MIT License
Classifier: Natural Language :: English
Classifier: Programming Language :: Python
Classifier: Programming Language :: Python :: 2
Classifier: Programming Language :: Python :: 2.7
Classifier: Development Status :: 3 - Alpha
Requires-Dist: wagtail-streamfieldtools (>=0.1)
